odoo8_addon_account_invoice_rounding_by_currency-8.0.1.0.0.99.dev2-py2.7-nspkg.pth
odoo8_addon_account_invoice_rounding_by_currency-8.0.1.0.0.99.dev2.dist-info/METADATA
odoo8_addon_account_invoice_rounding_by_currency-8.0.1.0.0.99.dev2.dist-info/RECORD
odoo8_addon_account_invoice_rounding_by_currency-8.0.1.0.0.99.dev2.dist-info/WHEEL
odoo8_addon_account_invoice_rounding_by_currency-8.0.1.0.0.99.dev2.dist-info/namespace_packages.txt
odoo8_addon_account_invoice_rounding_by_currency-8.0.1.0.0.99.dev2.dist-info/top_level.txt
odoo_addons/account_invoice_rounding_by_currency/README.rst
odoo_addons/account_invoice_rounding_by_currency/__init__.py
odoo_addons/account_invoice_rounding_by_currency/__openerp__.py
odoo_addons/account_invoice_rounding_by_currency/demo/data.xml
odoo_addons/account_invoice_rounding_by_currency/i18n/it.po
odoo_addons/account_invoice_rounding_by_currency/models/__init__.py
odoo_addons/account_invoice_rounding_by_currency/models/account.py
odoo_addons/account_invoice_rounding_by_currency/models/company.py
odoo_addons/account_invoice_rounding_by_currency/models/res_config.py
odoo_addons/account_invoice_rounding_by_currency/security/ir.model.access.csv
odoo_addons/account_invoice_rounding_by_currency/static/description/icon.png
odoo_addons/account_invoice_rounding_by_currency/tests/__init__.py
odoo_addons/account_invoice_rounding_by_currency/tests/test_rounding_by_currencies.py
odoo_addons/account_invoice_rounding_by_currency/views/res_config_view.xml
